nilrag/__init__.py
nilrag/config.py
nilrag/nildb_requests.py
nilrag/util.py
nilrag-0.1.11.dist-info/licenses/LICENSE
nilrag-0.1.11.dist-info/METADATA
nilrag-0.1.11.dist-info/WHEEL
nilrag-0.1.11.dist-info/top_level.txt
nilrag-0.1.11.dist-info/RECORD
