Metadata-Version: 2.4
Name: nilrag
Version: 0.1.11
Summary: nilRAG SDK
Author-email: Manuel Santos <manuel.santos@nillion.com>, Dimitris Mouris <dimitris@nillion.com>, Georgios Pentafragkas <georgios.pentafragkas@nillion.com>
Requires-Python: >=3.11
License-File: LICENSE
Requires-Dist: aiohttp>=3.11.14
Requires-Dist: ecdsa>=0.19.0
Requires-Dist: faker>=37.0.0
Requires-Dist: nilql==0.0.0a12
Requires-Dist: numpy<2.0.0
Requires-Dist: PyJWT[crypto]~=2.10.1
Requires-Dist: sentence-transformers>=3.3.1
Dynamic: license-file
